{"data":{"user":{"name":"Raj Karmakar","bio":"","isHireable":true,"avatarUrl":"https://avatars.githubusercontent.com/u/36797892?u=5b453340ec6976c35195d21e0f48c4f728368109&v=4","location":"Bengaluru, Karnataka","pinnedItems":{"totalCount":4,"edges":[{"node":{"name":"180-Top-SDE-Interview-Problems","description":null,"forkCount":0,"stargazers":{"totalCount":0},"url":"https://github.com/raj5036/180-Top-SDE-Interview-Problems","id":"MDEwOlJlcG9zaXRvcnkyNzMxNDcwMjI=","diskUsage":54129,"primaryLanguage":{"name":"Java","color":"#b07219"}}},{"node":{"name":"CodeChef","description":null,"forkCount":0,"stargazers":{"totalCount":0},"url":"https://github.com/raj5036/CodeChef","id":"MDEwOlJlcG9zaXRvcnkzMDUyNjA3MzE=","diskUsage":6468,"primaryLanguage":{"name":"C++","color":"#f34b7d"}}},{"node":{"name":"Competitive-Coding-Using-Java","description":null,"forkCount":0,"stargazers":{"totalCount":0},"url":"https://github.com/raj5036/Competitive-Coding-Using-Java","id":"MDEwOlJlcG9zaXRvcnkyNjQxMDE4MjM=","diskUsage":7041,"primaryLanguage":{"name":"Java","color":"#b07219"}}},{"node":{"name":"Codewars-Solutions","description":null,"forkCount":0,"stargazers":{"totalCount":0},"url":"https://github.com/raj5036/Codewars-Solutions","id":"MDEwOlJlcG9zaXRvcnkzMDMxNDc5NjI=","diskUsage":1962,"primaryLanguage":{"name":"C++","color":"#f34b7d"}}}]}}}}